{
  "batch": 33,
  "pages": [
    {
      "pdf_name": "2021_tier1_prepp_shift1",
      "page_number": 39,
      "merged_path": "pipeline_output\\p2_gemini\\2021_tier1_prepp_shift1\\merged_questions_global_order.json",
      "page_image_path": "pipeline_output\\p2_gemini\\2021_tier1_prepp_shift1\\page_images\\page_39.png"
    },
    {
      "pdf_name": "2021_tier1_prepp_shift1",
      "page_number": 40,
      "merged_path": "pipeline_output\\p2_gemini\\2021_tier1_prepp_shift1\\merged_questions_global_order.json",
      "page_image_path": "pipeline_output\\p2_gemini\\2021_tier1_prepp_shift1\\page_images\\page_40.png"
    },
    {
      "pdf_name": "2021_tier1_prepp_shift1",
      "page_number": 41,
      "merged_path": "pipeline_output\\p2_gemini\\2021_tier1_prepp_shift1\\merged_questions_global_order.json",
      "page_image_path": "pipeline_output\\p2_gemini\\2021_tier1_prepp_shift1\\page_images\\page_41.png"
    },
    {
      "pdf_name": "2021_tier1_prepp_shift1",
      "page_number": 42,
      "merged_path": "pipeline_output\\p2_gemini\\2021_tier1_prepp_shift1\\merged_questions_global_order.json",
      "page_image_path": "pipeline_output\\p2_gemini\\2021_tier1_prepp_shift1\\page_images\\page_42.png"
    }
  ]
}